[
    {
        "name": "Computer Networking & Security",
        "code": "CNS",
        "slots": 3,
        "coverage": [
            "PP",
            "PS",
            "OM",
            "KL",
            "NM",
            "AS"
        ],
        "ignore": []
    },
    {
        "name": "Software Development",
        "code": "SD",
        "slots": 3,
        "coverage": [
            "MP",
            "MS",
            "KL"
        ],
        "ignore": []
    },
    {
        "name": "Object-Oriented Programming",
        "code": "OOP",
        "slots": 4,
        "coverage": [
            "PS",
            "MS",
            "KL",
            "NM",
            "AS",
            "OM"
        ],
        "ignore": []
    },
    {
        "name": "Coding Questions",
        "code": "CQ",
        "slots": 7,
        "coverage": [
            "MP",
            "SM",
            "PS",
            "MS",
            "NM",
            "AS",
            "OM"
        ],
        "ignore": []
    },
    {
        "name": "Database Management System",
        "code": "DBMS",
        "slots": 3,
        "coverage": [
            "SM",
            "PP",
            "OM"
        ],
        "ignore": []
    },
    {
        "name": "Aptitude",
        "code": "APPT",
        "slots": 3,
        "coverage": [
            "SR",
            "MS",
            "RG"
        ],
        "ignore": []
    },
    {
        "name": "Data Structure and Algorithms",
        "code": "DSA",
        "slots": 7,
        "coverage": [
            "PP",
            "PS",
            "RG",
            "SR",
            "MP",
            "SM"
        ],
        "ignore": []
    },
    {
        "name": "Verbal Ability",
        "code": "VA",
        "slots": 3,
        "coverage": [
            "RG",
            "SR",
            "PP"
        ],
        "ignore": []
    }
]